[
  {
    "id": "ppg_reserve_brisk_frames",
    "name": "Brisk Frames (PPG)",
    "type": "Bonus",
    "label": "Bonus",
    "description": "For use on frames with less than <b><span style='font-variant: small-caps;'>3 Speed</span></b>. Equip to replace <b><span style='font-variant: small-caps;'>Speed</span></b> value with <b>3</b>.",
    "bonuses": [
      {
        "id": "speed",
        "val": 3,
        "replace": true
      }
    ]
  },
  {
    "id": "ppg_reserve_sensible_sensors",
    "name": "Sensible Sensors (PPG)",
    "type": "Bonus",
    "label": "Bonus",
    "description": "For use on frames with less than <b><span style='font-variant: small-caps;'>5 Sensors</span></b>. Equip to replace <b><span style='font-variant: small-caps;'>Sensors</span></b> value with <b>5</b>.",
    "bonuses": [
      {
        "id": "sensor",
        "val": 5,
        "replace": true
      }
    ]
  },
  {
    "id": "ppg_reserve_faster",
    "name": "Faster (PPG)",
    "type": "Bonus",
    "label": "Bonus",
    "description": "When forbidding actions from splitting up movement, increase the base <b><span style='font-variant: small-caps;'>Speed</span></b> of all characters by <b>1</b>.",
    "bonuses": [
      {
        "id": "speed",
        "val": 1
      }
    ]
  }
]